init_attrs_with_kwargs/__init__.py
tests/__init__.py
tests/test_init_attrs_with_func.py
tests/test_init_attrs_with_kwargs.py
tests/test_run_with_docopt.py
init_attrs_with_kwargs-0.2.0.dist-info/LICENSE
init_attrs_with_kwargs-0.2.0.dist-info/METADATA
init_attrs_with_kwargs-0.2.0.dist-info/WHEEL
init_attrs_with_kwargs-0.2.0.dist-info/top_level.txt
init_attrs_with_kwargs-0.2.0.dist-info/RECORD
