Metadata-Version: 2.1
Name: init-attrs-with-kwargs
Version: 0.2.0
Summary: A helper for type-checked command-line argument store
Home-page: https://github.com/tos-kamiya/init_attrs_with_kwargs
Author: Toshihiro kamiya
Author-email: kamiya@mbj.nifty.com
License: BSD 2-Clause License
Platform: UNKNOWN
Classifier: Programming Language :: Python :: 3.8
Classifier: Programming Language :: Python :: 3.9
Classifier: Programming Language :: Python :: 3.10
Classifier: License :: OSI Approved :: BSD License
Classifier: License :: Public Domain
Classifier: Operating System :: POSIX :: Linux
Classifier: Operating System :: Microsoft :: Windows :: Windows 10
Requires-Python: >=3.8
License-File: LICENSE
